cc_validator/__init__.py
cc_validator/__main__.py
cc_validator/canonical_pipeline.py
cc_validator/canonical_processors.py
cc_validator/cli_formatter.py
cc_validator/config.py
cc_validator/error_handlers.py
cc_validator/file_categorization.py
cc_validator/file_storage.py
cc_validator/main.py
cc_validator/processor_factories.py
cc_validator/pytest_plugin.py
cc_validator/reporters.py
cc_validator/validation_dataclasses.py
cc_validator/validation_logic.py
cc_validator-2.6.1.dist-info/METADATA
cc_validator-2.6.1.dist-info/WHEEL
cc_validator-2.6.1.dist-info/entry_points.txt
cc_validator-2.6.1.dist-info/licenses/LICENSE
cc_validator-2.6.1.dist-info/RECORD
