Metadata-Version: 2.4
Name: cc-validator
Version: 2.6.1
Summary: Hybrid security + TDD validation for Claude Code with automatic test result capture using Google Gemini
Project-URL: Homepage, https://github.com/jihunkim0/jk-hooks-gemini-challenge
Project-URL: Repository, https://github.com/jihunkim0/jk-hooks-gemini-challenge.git
Project-URL: Issues, https://github.com/jihunkim0/jk-hooks-gemini-challenge/issues
Project-URL: Documentation, https://github.com/jihunkim0/jk-hooks-gemini-challenge#readme
Author-email: Jihun Kim <jihunkim0@noreply.github.com>
License-Expression: MIT
License-File: LICENSE
Keywords: adk,ai-safety,claude-code,gemini,hooks,security,tdd,test-driven-development,validation
Classifier: Development Status :: 5 - Production/Stable
Classifier: Intended Audience :: Developers
Classifier: License :: OSI Approved :: MIT License
Classifier: Operating System :: OS Independent
Classifier: Programming Language :: Python :: 3
Classifier: Programming Language :: Python :: 3.12
Classifier: Programming Language :: Python :: 3.13
Classifier: Topic :: Security
Classifier: Topic :: Software Development :: Quality Assurance
Classifier: Topic :: Software Development :: Testing
Requires-Python: >=3.12
Requires-Dist: aiohttp>=3.12.15
Requires-Dist: dataclasses-json>=0.6.7
Requires-Dist: genai-processors>=0.1.0
Requires-Dist: google-genai>=1.25.0
Requires-Dist: pydantic>=2.0.0
Provides-Extra: dev
Requires-Dist: black>=23.0.0; extra == 'dev'
Requires-Dist: mypy>=1.0.0; extra == 'dev'
Requires-Dist: pytest>=7.0.0; extra == 'dev'
Requires-Dist: ruff>=0.1.0; extra == 'dev'
